preprocessing/__init__.py
preprocessing/deck/__init__.py
preprocessing/deck/ecl_deck.py
preprocessing/deck/runspec.py
preprocessing/deck/section.py
preprocessing/facilities/__init__.py
preprocessing/facilities/flowline.py
preprocessing/facilities/network.py
preprocessing/facilities/sampling_data.py
preprocessing/modular/__init__.py
preprocessing/modular/dat.py
preprocessing/modular/data.py
preprocessing/modular/egrid.py
preprocessing/modular/grdecl.py
preprocessing/modular/init.py
preprocessing/modular/s.py
preprocessing/modular/x.py
preprocessing/patches.py
preprocessing/utils/__init__.py
preprocessing/utils/expand_dates.py
preprocessing/utils/expand_wcon.py
preprocessing/utils/times.py
proteus_preprocessing-0.4.10.dist-info/METADATA
proteus_preprocessing-0.4.10.dist-info/WHEEL
proteus_preprocessing-0.4.10.dist-info/RECORD
