Metadata-Version: 2.1
Name: proteus-preprocessing
Version: 0.4.10
Summary: 
Requires-Python: >=3.8,<4.0
Classifier: Programming Language :: Python :: 3
Classifier: Programming Language :: Python :: 3.8
Classifier: Programming Language :: Python :: 3.9
Classifier: Programming Language :: Python :: 3.10
Classifier: Programming Language :: Python :: 3.11
Requires-Dist: ecl2df (==0.16.1)
Requires-Dist: h5py (>=3.6.0,<4.0.0)
Requires-Dist: libecl (==2.13.2)
Requires-Dist: opm (==2022.4)
Requires-Dist: pandas (>=1.4.1,<2.0.0)
Requires-Dist: python-json-logger (>=2.0.1,<3.0.0)
Requires-Dist: readchar (>=3.0.4,<4.0.0)
Requires-Dist: scikit-network (>=0.31.0,<0.32.0)
Requires-Dist: tabulate (>=0.8.9,<0.9.0)
Requires-Dist: tqdm (>=4.61.0,<5.0.0)
